{
	"archive" : {},
	"artifacts" : 
	[
		{
			"path" : "utils/libutils.a"
		}
	],
	"backtrace" : 1,
	"backtraceGraph" : 
	{
		"commands" : 
		[
			"add_library"
		],
		"files" : 
		[
			"utils/CMakeLists.txt"
		],
		"nodes" : 
		[
			{
				"file" : 0
			},
			{
				"command" : 0,
				"file" : 0,
				"line" : 14,
				"parent" : 0
			}
		]
	},
	"id" : "utils::@c810615cce0f7acb82dc",
	"name" : "utils",
	"nameOnDisk" : "libutils.a",
	"paths" : 
	{
		"build" : "utils",
		"source" : "utils"
	},
	"sourceGroups" : 
	[
		{
			"name" : "Header Files",
			"sourceIndexes" : 
			[
				0,
				1,
				2,
				3,
				4,
				5,
				6,
				7,
				8
			]
		}
	],
	"sources" : 
	[
		{
			"backtrace" : 1,
			"path" : "utils/exponential_moving_average.h",
			"sourceGroupIndex" : 0
		},
		{
			"backtrace" : 1,
			"path" : "utils/fsr.h",
			"sourceGroupIndex" : 0
		},
		{
			"backtrace" : 1,
			"path" : "utils/imu.h",
			"sourceGroupIndex" : 0
		},
		{
			"backtrace" : 1,
			"path" : "utils/joints.h",
			"sourceGroupIndex" : 0
		},
		{
			"backtrace" : 1,
			"path" : "utils/point_2d.h",
			"sourceGroupIndex" : 0
		},
		{
			"backtrace" : 1,
			"path" : "utils/point_3d.h",
			"sourceGroupIndex" : 0
		},
		{
			"backtrace" : 1,
			"path" : "utils/position.h",
			"sourceGroupIndex" : 0
		},
		{
			"backtrace" : 1,
			"path" : "utils/stl_ext.h",
			"sourceGroupIndex" : 0
		},
		{
			"backtrace" : 1,
			"path" : "utils/state.h",
			"sourceGroupIndex" : 0
		}
	],
	"type" : "STATIC_LIBRARY"
}
